{
  "title": "Button group",
  "description": "The button group component is used to switch between different views.",
  "postid": "button-group",
  "identifier": "Bg",
  "category": "components",
  "public": true,
  "themable": true,
  "contributors": {
    "dev": [
      {
        "name": "Daniel Kaneider",
        "githubuser": "danielkaneider"
      },
      {
        "name": "Thomas Heller",
        "githubuser": "tomheller"
      }
    ],
    "ux": [
      {
        "name": "Raphaela Raudaschl",
        "githubuser": "rrcaptain"
      }
    ]
  },
  "related": ["chart", "button", "tabs"],
  "tags": ["tabs", "component", "angular", "button", "buttongroup"],
  "imageUrl": "https://dt-cdn.net/images/barista-preview-button-group-624-214b6e04bd.png"
}
