{
  "title": "Expandable section",
  "description": "The expandable section is used to show and hide context information.",
  "postid": "expandable-section",
  "category": "components",
  "contributors": {
    "dev": [
      {
        "name": "Lara Aigmueller",
        "gitHubUser": "lara-aigmueller"
      }
    ],
    "ux": [
      {
        "name": "Gabriele Hasson-Birkenmayer",
        "gitHubUser": "GabrieleHB"
      }
    ]
  },
  "tags": ["expandable", "expandable section", "angular", "component"]
}
